[{"views":"1237","url":"https://www.tiktok.com/@sp.gouda/video/7562937705743600929"},{"views":"487","url":"https://www.tiktok.com/@sp.gouda/video/7558006518789066016"},{"views":"1229","url":"https://www.tiktok.com/@sp.gouda/video/7555886630662343969"},{"views":"1170","url":"https://www.tiktok.com/@sp.gouda/video/7545500087636593953"},{"views":"332","url":"https://www.tiktok.com/@sp.gouda/photo/7534609274605964577"},{"views":"1049","url":"https://www.tiktok.com/@sp.gouda/video/7534314978015333665"},{"views":"1110","url":"https://www.tiktok.com/@sp.gouda/video/7534313751709797665"}]